{
  "code": "0000",
  "msg": "操作成功",
  "data": {
    "sum": 10757,
    "successNum": 10757,
    "sucessRate": "1.00",
    "money": 79955000,
    "total": "80000000.00",
    "used": "79999000.00",
    "balance": "1000.00",
    "successPay": "0",
    "taxInclusiveSum": "2667799095.00",
    "noTaxInclusiveSum": "2360883525.00",
    "subSumList": [
      {
        "sum": 640,
        "successNum": 640,
        "sucessRate": null,
        "subsidiesLevel": "3000",
        "money": 1920000,
        "noTaxInclusiveSumSub": "50592634.00",
        "balance": 0
      },
      {
        "sum": 2520,
        "successNum": 2520,
        "sucessRate": null,
        "subsidiesLevel": "5000",
        "money": 12600000,
        "noTaxInclusiveSumSub": "371640340.00",
        "balance": 0
      },
      {
        "sum": 6044,
        "successNum": 6044,
        "sucessRate": null,
        "subsidiesLevel": "8000",
        "money": 48352000,
        "noTaxInclusiveSumSub": "1366164691.00",
        "balance": 0
      },
      {
        "sum": 1553,
        "successNum": 1553,
        "sucessRate": null,
        "subsidiesLevel": "11000",
        "money": 17083000,
        "noTaxInclusiveSumSub": "572485860.00",
        "balance": 0
      }
    ]
  }
}