{"code":"0000","msg":"操作成功","data":{"sum":3440,"successNum":3440,"sucessRate":"1.00","money":13003000,"total":"30000000.00","used":"13001000.00","balance":"16999000.00","successPay":"0","taxInclusiveSum":"870141085.00","noTaxInclusiveSum":"770036265.00","subSumList":[{"sum":269,"successNum":269,"sucessRate":null,"subsidiesLevel":"1000","money":269000,"noTaxInclusiveSumSub":"21708129.00","balance":0},{"sum":623,"successNum":623,"sucessRate":null,"subsidiesLevel":"2000","money":1246000,"noTaxInclusiveSumSub":"89421427.00","balance":0},{"sum":1900,"successNum":1900,"sucessRate":null,"subsidiesLevel":"4000","money":7600000,"noTaxInclusiveSumSub":"432612643.00","balance":0},{"sum":648,"successNum":648,"sucessRate":null,"subsidiesLevel":"6000","money":3888000,"noTaxInclusiveSumSub":"226294066.00","balance":0}]}}