{
  "code": "0000",
  "msg": "操作成功",
  "data": {
    "sum": 4922,
    "successNum": 4922,
    "sucessRate": "1.00",
    "money": 36659000,
    "total": "80000000.00",
    "used": "36678000.00",
    "balance": "43322000.00",
    "successPay": "0",
    "taxInclusiveSum": "1249841364.00",
    "noTaxInclusiveSum": "1106054067.00",
    "subSumList": [
      {
        "sum": 267,
        "successNum": 267,
        "sucessRate": null,
        "subsidiesLevel": "3000",
        "money": 801000,
        "noTaxInclusiveSumSub": "21268793.00",
        "balance": 0
      },
      {
        "sum": 1346,
        "successNum": 1346,
        "sucessRate": null,
        "subsidiesLevel": "5000",
        "money": 6730000,
        "noTaxInclusiveSumSub": "198117267.00",
        "balance": 0
      },
      {
        "sum": 2420,
        "successNum": 2420,
        "sucessRate": null,
        "subsidiesLevel": "8000",
        "money": 19360000,
        "noTaxInclusiveSumSub": "554085855.00",
        "balance": 0
      },
      {
        "sum": 888,
        "successNum": 888,
        "sucessRate": null,
        "subsidiesLevel": "11000",
        "money": 9768000,
        "noTaxInclusiveSumSub": "332551090.00",
        "balance": 0
      }
    ]
  }
}