{"code":"0000","msg":"操作成功","data":{"sum":3473,"successNum":3473,"sucessRate":"1.00","money":13135000,"total":"30000000.00","used":"13133000.00","balance":"16867000.00","successPay":"0","taxInclusiveSum":"878375185.00","noTaxInclusiveSum":"777323078.00","subSumList":[{"sum":271,"successNum":271,"sucessRate":null,"subsidiesLevel":"1000","money":271000,"noTaxInclusiveSumSub":"21861757.00","balance":0},{"sum":625,"successNum":625,"sucessRate":null,"subsidiesLevel":"2000","money":1250000,"noTaxInclusiveSumSub":"89694879.00","balance":0},{"sum":1924,"successNum":1924,"sucessRate":null,"subsidiesLevel":"4000","money":7696000,"noTaxInclusiveSumSub":"437961314.00","balance":0},{"sum":653,"successNum":653,"sucessRate":null,"subsidiesLevel":"6000","money":3918000,"noTaxInclusiveSumSub":"227805128.00","balance":0}]}}