{
  "code": "0000",
  "msg": "操作成功",
  "data": {
    "sum": 4213,
    "successNum": 4213,
    "sucessRate": "1.00",
    "money": 31895000,
    "total": "80000000.00",
    "used": "31876000.00",
    "balance": "48124000.00",
    "successPay": "0",
    "taxInclusiveSum": "1088711707.00",
    "noTaxInclusiveSum": "963461487.00",
    "subSumList": [
      {
        "sum": 194,
        "successNum": 194,
        "sucessRate": null,
        "subsidiesLevel": "3000",
        "money": 582000,
        "noTaxInclusiveSumSub": "15499641.00",
        "balance": 0
      },
      {
        "sum": 1069,
        "successNum": 1069,
        "sucessRate": null,
        "subsidiesLevel": "5000",
        "money": 5345000,
        "noTaxInclusiveSumSub": "159529229.00",
        "balance": 0
      },
      {
        "sum": 2157,
        "successNum": 2157,
        "sucessRate": null,
        "subsidiesLevel": "8000",
        "money": 17256000,
        "noTaxInclusiveSumSub": "492788169.00",
        "balance": 0
      },
      {
        "sum": 792,
        "successNum": 792,
        "sucessRate": null,
        "subsidiesLevel": "11000",
        "money": 8712000,
        "noTaxInclusiveSumSub": "295613386.00",
        "balance": 0
      }
    ]
  }
}