{
  "code": "0000",
  "msg": "操作成功",
  "data": {
    "sum": 10663,
    "successNum": 10663,
    "sucessRate": "1.00",
    "money": 79297000,
    "total": "80000000.00",
    "used": "79349000.00",
    "balance": "651000.00",
    "successPay": "0",
    "taxInclusiveSum": "2646106014.00",
    "noTaxInclusiveSum": "2341686115.00",
    "subSumList": [
      {
        "sum": 631,
        "successNum": 631,
        "sucessRate": null,
        "subsidiesLevel": "3000",
        "money": 1893000,
        "noTaxInclusiveSumSub": "49937590.00",
        "balance": 0
      },
      {
        "sum": 2488,
        "successNum": 2488,
        "sucessRate": null,
        "subsidiesLevel": "5000",
        "money": 12440000,
        "noTaxInclusiveSumSub": "366993302.00",
        "balance": 0
      },
      {
        "sum": 6003,
        "successNum": 6003,
        "sucessRate": null,
        "subsidiesLevel": "8000",
        "money": 48024000,
        "noTaxInclusiveSumSub": "1356823435.00",
        "balance": 0
      },
      {
        "sum": 1540,
        "successNum": 1540,
        "sucessRate": null,
        "subsidiesLevel": "11000",
        "money": 16940000,
        "noTaxInclusiveSumSub": "567912673.00",
        "balance": 0
      }
    ]
  }
}