{
  "code": "0000",
  "msg": "操作成功",
  "data": {
    "sum": 4202,
    "successNum": 4202,
    "sucessRate": "1.00",
    "money": 31810000,
    "total": "80000000.00",
    "used": "31791000.00",
    "balance": "48209000.00",
    "successPay": "0",
    "taxInclusiveSum": "1086101107.00",
    "noTaxInclusiveSum": "961151223.00",
    "subSumList": [
      {
        "sum": 194,
        "successNum": 194,
        "sucessRate": null,
        "subsidiesLevel": "3000",
        "money": 582000,
        "noTaxInclusiveSumSub": "15499641.00",
        "balance": 0
      },
      {
        "sum": 1067,
        "successNum": 1067,
        "sucessRate": null,
        "subsidiesLevel": "5000",
        "money": 5335000,
        "noTaxInclusiveSumSub": "159299495.00",
        "balance": 0
      },
      {
        "sum": 2149,
        "successNum": 2149,
        "sucessRate": null,
        "subsidiesLevel": "8000",
        "money": 17192000,
        "noTaxInclusiveSumSub": "491018258.00",
        "balance": 0
      },
      {
        "sum": 791,
        "successNum": 791,
        "sucessRate": null,
        "subsidiesLevel": "11000",
        "money": 8701000,
        "noTaxInclusiveSumSub": "295302767.00",
        "balance": 0
      }
    ]
  }
}